Metadata-Version: 1.1
Name: pylzmat
Version: 1.1.3
Summary: lzmat bindings.
Home-page: https://github.com/wiredrat/pylzmat
Author: Marcos Agüero
Author-email: wiredrat@gmail.com
License: GNU GPLv2
Platform: UNKNOWN
Classifier: Development Status :: 4 - Beta
Classifier: Intended Audience :: Developers
Classifier: License :: OSI Approved :: GNU General Public License (GPL)
Classifier: Operating System :: OS Independent
Classifier: Programming Language :: Python
Classifier: Topic :: Software Development :: Libraries :: Python Modules
